{"title": "CrockPot Pepperoni Chicken", "image": "https://media.popculture.com/2019/08/slow-cooker-pepperoni-and-chicken-resized-1-1--20067808.jpeg?auto=webp&width=650&height=430&crop=650:430,smart ", "cook_time": "6 hours", "servings": "6", "calories_per_serving": "305", "ingredients": ["2lbs chicken breast", " 1 cup chicken broth", " 3 tbsp tomato paste", " \u00bd onion (diced)", " 35 turkey pepperoni (sliced in half)", " 1 tsp Italian seasoning", " \u00bd tsp dried basil", " \u00bd tsp dried oregano", " \u00bc tsp red pepper flakes", " \u00bd cup sliced black olives"], "directions": "Put chicken on bottom of slow cooker and season with salt and pepper. /p In a medium bowl, stir together chicken broth, tomato paste, Italian Seasoning, Red Pepper flakes, basil, oregano, and diced onion. /p Pour over slow cooker. Add pepperoni and olives. /p Cover and cook for 3 hours on high or 6 hours on low, or until the chicken falls apart and can be easily shredded. /p Shred the chicken, then return to the slow cooker to absorb the juices for up to another hour. /p Serving Size: 1/6 of total yield (about 1 cup) /p Calories 307 ", "references": [{"name": "Pop Culture", "link": " https://popculture.com/lifestyle/news/recipe-slow-cooker-pepperoni-and-chicken/"}], "tags": ["Dinner", " Chicken", " Under 350 Calories", " Crockpot"]}